cipherLV/__init__.py
cipherLV/cipherLV.py
cipherLV-0.1.4.dist-info/LICENSE
cipherLV-0.1.4.dist-info/METADATA
cipherLV-0.1.4.dist-info/WHEEL
cipherLV-0.1.4.dist-info/top_level.txt
cipherLV-0.1.4.dist-info/RECORD
