Metadata-Version: 2.1
Name: cipherLV
Version: 0.1.4
Summary: Description: LV cipher is used for encrypting and decrypting with symmetric key
Home-page: UNKNOWN
Author: sarath babu
Author-email: sarathbabu.karunanithi@latentview.com
License: UNKNOWN
Keywords: python,encryption,decryption,cryptography
Platform: UNKNOWN
Classifier: Development Status :: 1 - Planning
Classifier: Intended Audience :: Developers
Classifier: Programming Language :: Python :: 3
Classifier: Operating System :: Unix
Classifier: Operating System :: MacOS :: MacOS X
Classifier: Operating System :: Microsoft :: Windows
